{
    "npcs": [
        {
            "npc_id": "npc_dispatcher",
            "display_name": "Paul",
            "character_id": "paul",
            "portrait": "profile",
            "dialogue_id": "dlg_dispatcher_offer",
            "dialogue_id_active": "dlg_dispatcher_active",
            "dialogue_id_repeat": "dlg_dispatcher_repeat",
            "patrol": {
                "min_x": 860,
                "max_x": 1020,
                "speed": 26
            },
            "idle_animation": "bob_slow",
            "barks": [
                "Check the board for new jobs.",
                { "text": "Town services need help. Head to the gate when ready.", "if": { "quest_active": "qt_main_town_welcome" } },
                { "text": "Good work restoring the relay. Keep exploring!", "if": { "quest_completed": "qt_main_town_relay" } }
            ],
            "interaction_radius": 170
        },
        {
            "npc_id": "npc_citizen",
            "display_name": "Local Citizen",
            "character_id": "bello",
            "portrait": "grid",
            "dialogue_id": "dlg_citizen_smalltalk",
            "patrol": {
                "min_x": 980,
                "max_x": 1280,
                "speed": 34
            },
            "idle_animation": "none",
            "idle_variants": ["none", "bob_slow"],
            "barks": {
                "chance": 0.58,
                "cooldown_ms_min": 9000,
                "cooldown_ms_max": 16000,
                "initial_delay_ms_min": 1700,
                "initial_delay_ms_max": 4200,
                "lines": [
                    "Nice weather for a walk.",
                    "Have you tried the cafe at the park?",
                    { "text": "I heard there's a hidden cache near the fences.", "if": { "flags_none": ["park_cache_found"] } }
                ]
            },
            "interaction_radius": 160
        },
        {
            "npc_id": "npc_guard",
            "display_name": "Town Guard",
            "character_id": "chase",
            "portrait": "grid",
            "dialogue_id": "dlg_guard_root",
            "patrol_path": {
                "speed": 42,
                "points": [
                    { "x": 980, "wait_ms_min": 450, "wait_ms_max": 950 },
                    { "x": 1120, "wait_ms_min": 450, "wait_ms_max": 1150 }
                ]
            },
            "idle_animation": "none",
            "idle_variants": ["none", "bob_slow"],
            "barks": [
                "Stay alert. Keep moving.",
                { "text": "If you find that missing poster, bring it to me.", "if": { "quest_active": "qt_side_missing_poster" } },
                { "text": "Thanks for helping the kid. Town morale matters.", "if": { "quest_completed": "qt_side_missing_poster" } }
            ],
            "interaction_radius": 170
        },
        {
            "npc_id": "npc_shopkeeper",
            "display_name": "Shopkeeper",
            "character_id": "bello",
            "portrait": "profile",
            "dialogue_id": "dlg_shopkeeper_root",
            "patrol_path": {
                "speed": 18,
                "points": [
                    { "x": 1280, "wait_ms": 800 },
                    { "x": 1400, "wait_ms": 700 }
                ]
            },
            "idle_animation": "bob_slow",
            "barks": [
                "Fresh stock arrives when the roads behave.",
                { "text": "Power is unstable. We need that cell delivered.", "if": { "quest_active": "qt_main_town_power" } },
                { "text": "Business is back! The shelves are humming again.", "if": { "quest_completed": "qt_main_town_relay" } }
            ],
            "interaction_radius": 160
        },
        {
            "npc_id": "npc_mechanic",
            "display_name": "Mechanic",
            "character_id": "donnie",
            "portrait": "grid",
            "dialogue_id": "dlg_mechanic_root",
            "patrol_path": {
                "speed": 22,
                "points": [
                    { "x": 2440, "wait_ms": 700 },
                    { "x": 2600, "wait_ms": 700 }
                ]
            },
            "idle_animation": "bob_fast",
            "barks": [
                "Tools ready. Just bring me parts.",
                { "text": "If you find a power cell, bring it here.", "if": { "quest_active": "qt_main_town_power" } },
                { "text": "Relay fixed? Perfect. I can breathe again.", "if": { "quest_completed": "qt_main_town_relay" } }
            ],
            "interaction_radius": 170
        },
        {
            "npc_id": "npc_investigator",
            "display_name": "Investigator",
            "character_id": "jerome",
            "portrait": "grid",
            "dialogue_id": "dlg_investigator_root",
            "patrol_path": {
                "speed": 26,
                "points": [
                    { "x": 1600, "wait_ms": 500 },
                    { "x": 1780, "wait_ms": 500 }
                ]
            },
            "idle_animation": "none",
            "barks": [
                "Clues don't find themselves.",
                { "text": "The terminal logs might tell us everything.", "if": { "quest_active": "qt_side_terminal_logs" } },
                { "text": "That cache key could unlock more than it seems.", "if": { "flags_all": ["park_cache_found"] } }
            ],
            "interaction_radius": 170
        },
        {
            "npc_id": "npc_informant",
            "display_name": "Informant",
            "character_id": "jerome",
            "portrait": "profile",
            "dialogue_id": "dlg_informant_root",
            "idle_animation": "bob_slow",
            "barks": [
                "I know a shortcut or two.",
                { "text": "Some doors open with the right item.", "if": { "flags_any": ["secret_alley_found", "park_cache_found"] } }
            ],
            "interaction_radius": 170
        },
        {
            "npc_id": "npc_digger",
            "display_name": "Digger",
            "character_id": "todd",
            "portrait": "grid",
            "dialogue_id": "dlg_digger_root",
            "patrol_path": {
                "speed": 24,
                "points": [
                    { "x": 3080, "wait_ms": 500 },
                    { "x": 3220, "wait_ms": 500 }
                ]
            },
            "idle_animation": "bob_fast",
            "barks": [
                "Soil tells a story.",
                { "text": "If you need something recovered, call Digging support.", "if": { "quest_active": "qt_side_buried_cache" } }
            ],
            "interaction_radius": 170
        },
        {
            "npc_id": "npc_customer",
            "display_name": "Customer",
            "character_id": "paul",
            "portrait": "grid",
            "dialogue_id": "dlg_customer_root",
            "idle_animation": "bob_slow",
            "barks": ["I ordered this ages ago...", "Maybe the park cafe has better luck."],
            "interaction_radius": 160
        },
        {
            "npc_id": "npc_resident",
            "display_name": "Resident",
            "character_id": "flip",
            "portrait": "grid",
            "dialogue_id": "dlg_resident_root",
            "idle_animation": "bob_slow",
            "barks": ["The park is peaceful... until it isn't.", "Watch for hidden paths by the fences."],
            "interaction_radius": 160
        },
        {
            "npc_id": "npc_kid",
            "display_name": "Kid",
            "character_id": "jett",
            "portrait": "grid",
            "dialogue_id": "dlg_kid_root",
            "idle_animation": "bob_fast",
            "barks": [
                "Zoom! But... I lost something.",
                { "text": "My poster is missing. Can you help?", "if": { "quest_active": "qt_side_missing_poster" } }
            ],
            "interaction_radius": 160
        },
        {
            "npc_id": "npc_officer",
            "display_name": "Officer",
            "character_id": "chase",
            "portrait": "profile",
            "dialogue_id": "dlg_officer_root",
            "idle_animation": "bob_slow",
            "barks": [
                "All clear so far.",
                { "text": "If you see trouble, call Police support.", "if": { "quest_active": "qt_side_garage_clearance" } }
            ],
            "interaction_radius": 160
        }
    ]
}
